LICENSE.txt
MANIFEST.in
README.rst
setup.py
djangocms_bulma_column/__init__.py
djangocms_bulma_column/cms_plugins.py
djangocms_bulma_column/forms.py
djangocms_bulma_column/models.py
djangocms_bulma_column.egg-info/PKG-INFO
djangocms_bulma_column.egg-info/SOURCES.txt
djangocms_bulma_column.egg-info/dependency_links.txt
djangocms_bulma_column.egg-info/not-zip-safe
djangocms_bulma_column.egg-info/requires.txt
djangocms_bulma_column.egg-info/top_level.txt
djangocms_bulma_column/migrations/0001_initial.py
djangocms_bulma_column/migrations/0002_multicolumns_extra_css.py
djangocms_bulma_column/migrations/__init__.py
djangocms_bulma_column/templates/cms/plugins/column.html
djangocms_bulma_column/templates/cms/plugins/column_edit.html
djangocms_bulma_column/templates/cms/plugins/multi_column.html